{
    "label" : "KNN Blocking",
    "git_status" : "modified",
    "git_branch" : "master",
    "git_revision" : "02dcdf5",
    "compiler" : "gcc",
    "compiler_flags" : "-std=c11 -Wall -lm -O3 -mavx -mavx2 -mfma -march=native",
    "debug" : false,
    "cpu" : "Intel(R) Core(TM) i7-1065G7 CPU @ 1.30GHz",
    "turbo_boost_disabled" : true,
    "arguments" : "-n 1 --label 1knn__exact_opt7 --impl exact -i 256 -i 512 -i 768 -i 1024 -i 1280 -i 1536 -i 1792 -i 2048 -i 2304 -i 2560 -i 2816 -i 3072 -i 3328 -i 3584 -i 3840 -i 4096 -i 4352 -i 4608 -i 4864 -i 5120 -i 5376 -i 5632 -i 5888 -i 6144 ",
    "implementation" : "exact",
    "implementation_correct" : true,
    "num_runs" : 1,
    "num_input_sizes" : 11,
    "input_sizes" : [256, 512, 768, 1024, 1280, 1536, 1792, 2048, 2304, 2560, 2816, 3072, 3328, 3584, 3840, 4096, 4352, 4608, 4864, 5120, 5376, 5632, 5888, 6144],


    "benchmarks" : {
        "256" : [
            270814083
        ],
        "512" : [
            1061270397
        ],
        "768" : [
            2384792600
        ],
        "1024" : [
            4253669989
        ],
        "1280" : [
            6881099669
        ],
        "1536" : [
            9813191482
        ],
        "1792" : [
            13488981620
        ],
        "2048" : [
            17902637707
        ],
        "2304" : [
            22018792458
        ],
        "2560" : [
            26888479816
        ],
        "2816" : [
            32688525938
        ],
        "3072" : [
            38780902535
        ],
        "3328" : [
            45611535269
        ],
        "3584" : [
            52843147480
        ],
        "3840" : [
            60844011829
        ],
        "4096" : [
            69358450990
        ],
        "4352" : [
            78165564011
        ],
        "4608" : [
            87658075308
        ],
        "4864" : [
            97811118581
        ],
        "5120" : [
            108580201805
        ],
        "5376" : [
            119546680087
        ],
        "5632" : [
            131602295053
        ],
        "5888" : [
            143814099632
        ],
        "6144" : [
            156556249631
        ]
    }
}
